setup.py
acm_distributions/Binomialdistribution.py
acm_distributions/Gaussiandistribution.py
acm_distributions/Generaldistribution.py
acm_distributions/__init__.py
acm_distributions.egg-info/PKG-INFO
acm_distributions.egg-info/SOURCES.txt
acm_distributions.egg-info/dependency_links.txt
acm_distributions.egg-info/not-zip-safe
acm_distributions.egg-info/top_level.txt